LICENSE
README.md
pyproject.toml
setup.cfg
pyfron/__init__.py
pyfron/__main__.py
pyfron/env.py
pyfron/preparation.py
pyfron/recognizers.py
pyfron/reports.py
pyfron/run.py
pyfron/structures.py
pyfron.egg-info/PKG-INFO
pyfron.egg-info/SOURCES.txt
pyfron.egg-info/dependency_links.txt
pyfron.egg-info/entry_points.txt
pyfron.egg-info/top_level.txt