Metadata-Version: 2.1
Name: pyfron
Version: 0.1.1
Summary: An OpenDR-based face recognition CLI app
Home-page: https://github.com/GeorgeVasiliadis/pyfron
Author: George Vasiliadis
Author-email: geor.vasiliadis@gmail.com
License: MIT
Classifier: Programming Language :: Python :: 3
Classifier: Topic :: Scientific/Engineering :: Artificial Intelligence
Classifier: Topic :: Scientific/Engineering :: Image Recognition
Classifier: Topic :: System
Classifier: License :: OSI Approved :: MIT License
Classifier: Operating System :: OS Independent
Requires-Python: >=3.6
License-File: LICENSE
